{
  "type": "minecraft:chest",
  "pools": [
    {
      "rolls": 1,
      "entries": [
        {
          "type": "minecraft:item",
          "name": "minecraft:book",
          "functions": [
            {
              "function": "minecraft:set_count",
              "count": {
                "min": 1,
                "max": 2
              }
            },
            {
              "function": "minecraft:enchant_with_levels",
              "levels": {
                "min": 5,
                "max": 20
              }
            }
          ]
        }
      ]
    },
    {
      "rolls": 1,
      "entries": [
        {
          "type": "minecraft:item",
          "name": "minecraft:book",
          "functions": [
            {
              "function": "minecraft:set_count",
              "count": {
                "min": 1,
                "max": 8
              }
            }
          ]
        },
        {
          "type": "minecraft:item",
          "name": "minecraft:redstone_torch"
        },
        {
          "type": "minecraft:item",
          "name": "minecraft:purple_dye",
          "functions": [
            {
              "function": "minecraft:set_count",
              "count": {
                "min": 1,
                "max": 2
              }
            }
          ]
        }
      ]
    },
    {
      "rolls": {
        "min": 1,
        "max": 2
      },
      "entries": [
        {
          "type": "minecraft:item",
          "weight": 50,
          "name": "minecraft:raw_gold",
          "functions": [
            {
              "function": "minecraft:set_count",
              "count": {
                "min": 1,
                "max": 4
              }
            }
          ]
        },
        {
          "type": "minecraft:item",
          "weight": 20,
          "name": "minecraft:raw_iron",
          "functions": [
            {
              "function": "minecraft:set_count",
              "count": {
                "min": 4,
                "max": 12
              }
            }
          ]
        }
      ]
    },
    {
      "rolls": {
        "min": 1,
        "max": 2
      },
      "entries": [
        {
          "type": "minecraft:empty",
          "weight": 20
        },
		{
          "type": "minecraft:loot_table",
          "name": "minecraft:armor/high_helmet_enchanted"
        },
		{
          "type": "minecraft:loot_table",
          "name": "minecraft:armor/high_chest_enchanted"
        },
		{
          "type": "minecraft:loot_table",
          "name": "minecraft:armor/high_leggings_enchanted"
        },
		{
          "type": "minecraft:loot_table",
          "name": "minecraft:armor/high_boots_enchanted"
        }
      ]
    }
  ]
}
